pacyam/__init__.py
pacyam/pacyam.py
pacyam-1.1.1.dist-info/LICENSE
pacyam-1.1.1.dist-info/METADATA
pacyam-1.1.1.dist-info/WHEEL
pacyam-1.1.1.dist-info/entry_points.txt
pacyam-1.1.1.dist-info/top_level.txt
pacyam-1.1.1.dist-info/RECORD
