Metadata-Version: 2.1
Name: pacyam
Version: 1.1.1
Summary: Command line program that makes designing and developing of multi-environment Packer images a breeze.
Home-page: https://github.com/dstarner/pacyam
Author: Daniel Starner
Author-email: starner.daniel5@gmail.com
License: UNKNOWN
Keywords: Packer,Vagrant,Virtualbox
Platform: UNKNOWN
Classifier: Programming Language :: Python :: 3
Classifier: License :: OSI Approved :: MIT License
Classifier: Operating System :: OS Independent
Requires-Python: >=3.7
Requires-Dist: Jinja2 (==2.10.3)
Requires-Dist: MarkupSafe (==1.1.1)
Requires-Dist: PyYAML (==5.1.2)
